stattools/__init__.py
stattools/cluster/__init__.py
stattools/cluster/k_means.py
stattools/datasets/__init__.py
stattools/datasets/load.py
stattools/datasets/data/lsat_gpa.csv
stattools/datasets/data/old_faithful.csv
stattools/ensemble/__init__.py
stattools/ensemble/bagging.py
stattools/generic/__init__.py
stattools/generic/fit.py
stattools/generic/ovr.py
stattools/generic/predictors.py
stattools/glm/__init__.py
stattools/glm/glm.py
stattools/glm/linear.py
stattools/glm/linear_penalized.py
stattools/glm/logistic.py
stattools/mixture/__init__.py
stattools/mixture/gaussian.py
stattools/optimization/__init__.py
stattools/optimization/base.py
stattools/optimization/gradient_descent.py
stattools/optimization/newton_raphson.py
stattools/preprocessing/__init__.py
stattools/preprocessing/base.py
stattools/preprocessing/pca.py
stattools/preprocessing/standardize.py
stattools/regularization/__init__.py
stattools/regularization/lasso_decorator.py
stattools/regularization/ridge_decorator.py
stattools/resampling/__init__.py
stattools/resampling/bootstrap.py
stattools/resampling/jackknife.py
stattools/resampling/permutation.py
stattools/simulation/__init__.py
stattools/simulation/ito.py
stattools/simulation/poisson.py
stattools/smoothing/__init__.py
stattools/smoothing/bin.py
stattools/smoothing/kde.py
stattools/smoothing/kernel.py
stattools/smoothing/knn.py
stattools/smoothing/polynomial.py
stattools/smoothing/smoothing.py
stattools/survival/__init__.py
stattools/survival/kaplan_meier.py
stattools/utils/__init__.py
stattools/utils/summary.py
stattools/utils/validation.py
stattools/visualization/__init__.py
stattools/visualization/classification.py
stattools/visualization/distributions.py
stattools/visualization/plotting.py
stattools-0.0.4.dist-info/METADATA
stattools-0.0.4.dist-info/RECORD
stattools-0.0.4.dist-info/WHEEL
stattools-0.0.4.dist-info/top_level.txt
