Metadata-Version: 2.1
Name: stattools
Version: 0.0.4
Summary: Statistical learning and inference library
Home-page: https://github.com/artemmavrin/StatTools
Author: Artem Mavrin
Author-email: amavrin@ucsd.edu
License: MIT
Platform: UNKNOWN
